splitem/__init__.py
splitem/cli.py
splitem/lib.py
splitem-0.1.0.dist-info/entry_points.txt
splitem-0.1.0.dist-info/WHEEL
splitem-0.1.0.dist-info/METADATA
splitem-0.1.0.dist-info/RECORD
